Workbook

Sheet FACTURE-PROFORMA
A1: =PARAMETRES!$B$4 | D1: ="WhatsApp : "&PARAMETRES!$B$5 | H1: ZONE DE TRAVAIL — COLONNES G À L NON IMPRIMÉES
A2: =PARAMETRES!$B$6
A3: Qualité, rapidité et confiance | D3: ="Réf. "&PARAMETRES!$B$7 | H3: TYPE DOCUMENT | I3: FACTURE
H4: STATUT | I4: BROUILLON
A5: =UPPER($I$3) | H5: Marge % défaut | I5: 0.3
H6: Devise | I6: =PARAMETRES!$B$8
A7: N° Document | C7: =IF($I$3="FACTURE",PARAMETRES!$B$11,PARAMETRES!$B$12)&"-"&PARAMETRES!$B$10&"-"&TEXT(COUNTIF('HISTORIQUE DOCS'!$C$4:$C$1000,$I$3)+1,"000") | E7: Date | F7: 46266 | H7: Année | I7: =PARAMETRES!$B$10
A8: ID Client | C8: CLI-0003 | E8: Lieu | F8: Lubumbashi
A9: CLIENT | H9: Contrôle stock | I9: =IF(COUNTIF(L15:L24,"STOCK INSUFFISANT")>0,"⚠ "&COUNTIF(L15:L24,"STOCK INSUFFISANT")& " ligne(s) au-dessus du stock","OK — stock suffisant")
A10: Nom / Société | C10: =IFERROR(TRIM(VLOOKUP($C$8,'BASE CLIENTS'!$A$4:$M$500,4,FALSE)&" "&VLOOKUP($C$8,'BASE CLIENTS'!$A$4:$M$500,3,FALSE)&" "&VLOOKUP($C$8,'BASE CLIENTS'!$A$4:$M$500,2,FALSE))&IF(VLOOKUP($C$8,'BASE CLIENTS'!$A$4:$M$500,5,FALSE)="","", " — "&VLOOKUP($C$8,'BASE CLIENTS'!$A$4:$M$500,5,FALSE)),"")
A11: Téléphone | C11: =IFERROR(VLOOKUP($C$8,'BASE CLIENTS'!$A$4:$M$500,6,FALSE),"") | E11: Ville | F11: =IFERROR(VLOOKUP($C$8,'BASE CLIENTS'!$A$4:$M$500,8,FALSE),"") | H11: Nb lignes remplies | I11: =COUNTA(B15:B24)
A12: Adresse | C12: =IFERROR(TRIM(VLOOKUP($C$8,'BASE CLIENTS'!$A$4:$M$500,10,FALSE)&" "&VLOOKUP($C$8,'BASE CLIENTS'!$A$4:$M$500,9,FALSE)),"") | H12: Cellules à fond gris clair = saisie. Toutes les autres cellules (formules) sont verrouillées.
A14: N° | B14: Réf. | C14: Désignation | D14: Qté | E14: P.U. USD | F14: Montant | H14: Transport | I14: Autres frais | J14: Stock dispo | K14: Marge % | L14: Alerte stock
A15: 1 | C15: =IFERROR(VLOOKUP($B15,'BASE ARTICLES'!$A$4:$P$500,2,FALSE),"") | E15: =IFERROR(VLOOKUP($B15,'BASE ARTICLES'!$A$4:$P$500,10,FALSE),"") | F15: =IF(OR($B15="",$D15=""),0,$D15*$E15+$H15+$I15) | H15: 0 | I15: 0 | J15: =IFERROR(VLOOKUP($B15,'BASE ARTICLES'!$A$4:$P$500,13,FALSE),"") | K15: =IFERROR(VLOOKUP($B15,'BASE ARTICLES'!$A$4:$P$500,9,FALSE),$I$5) | L15: =IF(OR($B15="",$D15=""),"",IF(N($J15)<N($D15),"STOCK INSUFFISANT","OK"))
A16: 2 | C16: =IFERROR(VLOOKUP($B16,'BASE ARTICLES'!$A$4:$P$500,2,FALSE),"") | E16: =IFERROR(VLOOKUP($B16,'BASE ARTICLES'!$A$4:$P$500,10,FALSE),"") | F16: =IF(OR($B16="",$D16=""),0,$D16*$E16+$H16+$I16) | H16: 0 | I16: 0 | J16: =IFERROR(VLOOKUP($B16,'BASE ARTICLES'!$A$4:$P$500,13,FALSE),"") | K16: =IFERROR(VLOOKUP($B16,'BASE ARTICLES'!$A$4:$P$500,9,FALSE),$I$5) | L16: =IF(OR($B16="",$D16=""),"",IF(N($J16)<N($D16),"STOCK INSUFFISANT","OK"))
A17: 3 | C17: =IFERROR(VLOOKUP($B17,'BASE ARTICLES'!$A$4:$P$500,2,FALSE),"") | E17: =IFERROR(VLOOKUP($B17,'BASE ARTICLES'!$A$4:$P$500,10,FALSE),"") | F17: =IF(OR($B17="",$D17=""),0,$D17*$E17+$H17+$I17) | H17: 0 | I17: 0 | J17: =IFERROR(VLOOKUP($B17,'BASE ARTICLES'!$A$4:$P$500,13,FALSE),"") | K17: =IFERROR(VLOOKUP($B17,'BASE ARTICLES'!$A$4:$P$500,9,FALSE),$I$5) | L17: =IF(OR($B17="",$D17=""),"",IF(N($J17)<N($D17),"STOCK INSUFFISANT","OK"))
A18: 4 | C18: =IFERROR(VLOOKUP($B18,'BASE ARTICLES'!$A$4:$P$500,2,FALSE),"") | E18: =IFERROR(VLOOKUP($B18,'BASE ARTICLES'!$A$4:$P$500,10,FALSE),"") | F18: =IF(OR($B18="",$D18=""),0,$D18*$E18+$H18+$I18) | H18: 0 | I18: 0 | J18: =IFERROR(VLOOKUP($B18,'BASE ARTICLES'!$A$4:$P$500,13,FALSE),"") | K18: =IFERROR(VLOOKUP($B18,'BASE ARTICLES'!$A$4:$P$500,9,FALSE),$I$5) | L18: =IF(OR($B18="",$D18=""),"",IF(N($J18)<N($D18),"STOCK INSUFFISANT","OK"))
A19: 5 | C19: =IFERROR(VLOOKUP($B19,'BASE ARTICLES'!$A$4:$P$500,2,FALSE),"") | E19: =IFERROR(VLOOKUP($B19,'BASE ARTICLES'!$A$4:$P$500,10,FALSE),"") | F19: =IF(OR($B19="",$D19=""),0,$D19*$E19+$H19+$I19) | H19: 0 | I19: 0 | J19: =IFERROR(VLOOKUP($B19,'BASE ARTICLES'!$A$4:$P$500,13,FALSE),"") | K19: =IFERROR(VLOOKUP($B19,'BASE ARTICLES'!$A$4:$P$500,9,FALSE),$I$5) | L19: =IF(OR($B19="",$D19=""),"",IF(N($J19)<N($D19),"STOCK INSUFFISANT","OK"))
A20: 6 | C20: =IFERROR(VLOOKUP($B20,'BASE ARTICLES'!$A$4:$P$500,2,FALSE),"") | E20: =IFERROR(VLOOKUP($B20,'BASE ARTICLES'!$A$4:$P$500,10,FALSE),"") | F20: =IF(OR($B20="",$D20=""),0,$D20*$E20+$H20+$I20) | H20: 0 | I20: 0 | J20: =IFERROR(VLOOKUP($B20,'BASE ARTICLES'!$A$4:$P$500,13,FALSE),"") | K20: =IFERROR(VLOOKUP($B20,'BASE ARTICLES'!$A$4:$P$500,9,FALSE),$I$5) | L20: =IF(OR($B20="",$D20=""),"",IF(N($J20)<N($D20),"STOCK INSUFFISANT","OK"))
A21: 7 | C21: =IFERROR(VLOOKUP($B21,'BASE ARTICLES'!$A$4:$P$500,2,FALSE),"") | E21: =IFERROR(VLOOKUP($B21,'BASE ARTICLES'!$A$4:$P$500,10,FALSE),"") | F21: =IF(OR($B21="",$D21=""),0,$D21*$E21+$H21+$I21) | H21: 0 | I21: 0 | J21: =IFERROR(VLOOKUP($B21,'BASE ARTICLES'!$A$4:$P$500,13,FALSE),"") | K21: =IFERROR(VLOOKUP($B21,'BASE ARTICLES'!$A$4:$P$500,9,FALSE),$I$5) | L21: =IF(OR($B21="",$D21=""),"",IF(N($J21)<N($D21),"STOCK INSUFFISANT","OK"))
A22: 8 | C22: =IFERROR(VLOOKUP($B22,'BASE ARTICLES'!$A$4:$P$500,2,FALSE),"") | E22: =IFERROR(VLOOKUP($B22,'BASE ARTICLES'!$A$4:$P$500,10,FALSE),"") | F22: =IF(OR($B22="",$D22=""),0,$D22*$E22+$H22+$I22) | H22: 0 | I22: 0 | J22: =IFERROR(VLOOKUP($B22,'BASE ARTICLES'!$A$4:$P$500,13,FALSE),"") | K22: =IFERROR(VLOOKUP($B22,'BASE ARTICLES'!$A$4:$P$500,9,FALSE),$I$5) | L22: =IF(OR($B22="",$D22=""),"",IF(N($J22)<N($D22),"STOCK INSUFFISANT","OK"))
A23: 9 | C23: =IFERROR(VLOOKUP($B23,'BASE ARTICLES'!$A$4:$P$500,2,FALSE),"") | E23: =IFERROR(VLOOKUP($B23,'BASE ARTICLES'!$A$4:$P$500,10,FALSE),"") | F23: =IF(OR($B23="",$D23=""),0,$D23*$E23+$H23+$I23) | H23: 0 | I23: 0 | J23: =IFERROR(VLOOKUP($B23,'BASE ARTICLES'!$A$4:$P$500,13,FALSE),"") | K23: =IFERROR(VLOOKUP($B23,'BASE ARTICLES'!$A$4:$P$500,9,FALSE),$I$5) | L23: =IF(OR($B23="",$D23=""),"",IF(N($J23)<N($D23),"STOCK INSUFFISANT","OK"))
A24: 10 | C24: =IFERROR(VLOOKUP($B24,'BASE ARTICLES'!$A$4:$P$500,2,FALSE),"") | E24: =IFERROR(VLOOKUP($B24,'BASE ARTICLES'!$A$4:$P$500,10,FALSE),"") | F24: =IF(OR($B24="",$D24=""),0,$D24*$E24+$H24+$I24) | H24: 0 | I24: 0 | J24: =IFERROR(VLOOKUP($B24,'BASE ARTICLES'!$A$4:$P$500,13,FALSE),"") | K24: =IFERROR(VLOOKUP($B24,'BASE ARTICLES'!$A$4:$P$500,9,FALSE),$I$5) | L24: =IF(OR($B24="",$D24=""),"",IF(N($J24)<N($D24),"STOCK INSUFFISANT","OK"))
A25: OBSERVATIONS | D25: Sous-total | F25: =SUM(F15:F24)
A26: Saisir ici les observations, garanties ou conditions particulières. | D26: Marge société | F26: =SUMPRODUCT(F15:F24,K15:K24) | H26: ✅ VALIDER & IMPRIMER — PDF A5 + Historique + Sortie de stock
D27: TOTAL GÉNÉRAL | F27: =F25+F26
A28: Conditions paiement | C28: =PARAMETRES!$B$15 | H28: 🧾 ENREGISTRER BROUILLON — sans sortie de stock
A30: ="Pour "&PARAMETRES!$B$4&CHAR(10)&CHAR(10)&"Signature & cachet" | D30: ="Client : "&$C$10&CHAR(10)&CHAR(10)&"Signature" | H30: 🧹 NOUVEAU DOCUMENT — formulaire vierge
H33: MAQUETTE — Dans la version finale automatisée, « VALIDER & IMPRIMER » génère le PDF au format A5, enregistre le document dans HISTORIQUE DOCS, met à jour le stock uniquement pour une FACTURE VALIDÉE, puis remet le formulaire à zéro. Une PROFORMA ne diminue jamais le stock. Les colonnes G à L ne sont pas imprimées : elles servent au calcul (transport, autres frais, stock, marge).
A34: =IF($I$3="PROFORMA","Proforma valable "&PARAMETRES!$B$16&" jours — ne vaut pas facture et n’entraîne aucune sortie de stock.","Merci de votre confiance — toute réclamation doit être formulée dans les 7 jours.")

Sheet BASE CLIENTS
A1: BASE DE DONNÉES CLIENTS | O1: FORMULAIRE — AJOUT CLIENT
A3: ID Client | B3: Nom | C3: Postnom | D3: Prénom | E3: Société | F3: Téléphone | G3: Téléphone 2 | H3: Ville | I3: Commune | J3: Adresse | K3: E-mail | L3: Type Client | M3: Observation | O3: Champ | P3: Saisie
A4: CLI-0001 | B4: DIENGA | D4: NONO | F4: 0995 339 979 | H4: Lubumbashi | L4: PARTICULIER | O4: Nom
A5: CLI-0002 | B5: MUKAZA | C5: SCHADRAK | D5: SONY | F5: 0995 003 367 | H5: Kolwezi | L5: PARTICULIER | O5: Postnom
A6: CLI-0003 | B6: KAYISA | D6: MATHIEU | F6: 0817 967 541 | H6: Lubumbashi | L6: PARTICULIER | O6: Prénom
A7: CLI-0004 | B7: CLIENT | D7: DEMO | E7: SOCIETE DEMO | F7: +243 000 000 000 | H7: Lubumbashi | L7: ENTREPRISE | M7: Test | O7: Société
O8: Téléphone
O9: Ville
O10: Commune
O11: Adresse
O12: Type client | P12: PARTICULIER
O14: ➕ AJOUTER CLIENT (Bouton maquette)

Sheet BASE ARTICLES
A1: BASE DE DONNÉES ARTICLES / SERVICES | R1: FORMULAIRE — NOUVEL ARTICLE
A3: Référence | B3: Désignation | C3: Catégorie | D3: Fournisseur | E3: Coût achat unitaire | F3: Transport unitaire | G3: Autres frais | H3: Coût de revient | I3: Marge % | J3: Prix vente conseillé | K3: Qté entrée | L3: Qté sortie | M3: Stock disponible | N3: Seuil alerte | O3: Garantie | P3: Observation | R3: Champ | S3: Saisie
A4: ART-0001 | B4: Radio Android Mercedes-Benz | C4: Auto / Multimédia | D4: Fournisseur A | E4: 100 | F4: 20 | G4: 0 | H4: =E4+F4+G4 | I4: 0.3 | J4: =H4*(1+I4) | K4: 5 | L4: =SUMIFS('HISTORIQUE DOCS'!$H$4:$H$1000,'HISTORIQUE DOCS'!$F$4:$F$1000,A4,'HISTORIQUE DOCS'!$C$4:$C$1000,"FACTURE",'HISTORIQUE DOCS'!$P$4:$P$1000,"VALIDÉ") | M4: =K4-L4 | N4: 2 | O4: Selon modèle | R4: Désignation
A5: ART-0002 | B5: Jante auto + capuchon central | C5: Auto / Jantes | D5: Fournisseur B | E5: 250 | F5: 50 | G5: 0 | H5: =E5+F5+G5 | I5: 0.3 | J5: =H5*(1+I5) | K5: 8 | L5: =SUMIFS('HISTORIQUE DOCS'!$H$4:$H$1000,'HISTORIQUE DOCS'!$F$4:$F$1000,A5,'HISTORIQUE DOCS'!$C$4:$C$1000,"FACTURE",'HISTORIQUE DOCS'!$P$4:$P$1000,"VALIDÉ") | M5: =K5-L5 | N5: 2 | O5: 3 ans finition / structure à vie | R5: Catégorie
A6: ART-0003 | B6: Samsung Galaxy A17 128G + 6G | C6: Téléphone | D6: Fournisseur C | E6: 220 | F6: 15 | G6: 0 | H6: =E6+F6+G6 | I6: 0.3 | J6: =H6*(1+I6) | K6: 6 | L6: =SUMIFS('HISTORIQUE DOCS'!$H$4:$H$1000,'HISTORIQUE DOCS'!$F$4:$F$1000,A6,'HISTORIQUE DOCS'!$C$4:$C$1000,"FACTURE",'HISTORIQUE DOCS'!$P$4:$P$1000,"VALIDÉ") | M6: =K6-L6 | N6: 2 | O6: 12 mois | R6: Fournisseur
A7: SRV-0001 | B7: Diagnostic automobile | C7: Service | D7: Interne | E7: 0 | F7: 0 | G7: 0 | H7: =E7+F7+G7 | I7: 1 | J7: =H7*(1+I7) | K7: 999 | L7: =SUMIFS('HISTORIQUE DOCS'!$H$4:$H$1000,'HISTORIQUE DOCS'!$F$4:$F$1000,A7,'HISTORIQUE DOCS'!$C$4:$C$1000,"FACTURE",'HISTORIQUE DOCS'!$P$4:$P$1000,"VALIDÉ") | M7: =K7-L7 | N7: 0 | O7: Service | R7: Coût achat
A8: SRV-0002 | B8: Installation radio Android | C8: Service | D8: Interne | E8: 0 | F8: 0 | G8: 0 | H8: =E8+F8+G8 | I8: 1 | J8: =H8*(1+I8) | K8: 999 | L8: =SUMIFS('HISTORIQUE DOCS'!$H$4:$H$1000,'HISTORIQUE DOCS'!$F$4:$F$1000,A8,'HISTORIQUE DOCS'!$C$4:$C$1000,"FACTURE",'HISTORIQUE DOCS'!$P$4:$P$1000,"VALIDÉ") | M8: =K8-L8 | N8: 0 | O8: Service | R8: Transport unitaire
H9: =E9+F9+G9 | J9: =H9*(1+I9) | L9: =SUMIFS('HISTORIQUE DOCS'!$H$4:$H$1000,'HISTORIQUE DOCS'!$F$4:$F$1000,A9,'HISTORIQUE DOCS'!$C$4:$C$1000,"FACTURE",'HISTORIQUE DOCS'!$P$4:$P$1000,"VALIDÉ") | M9: =K9-L9 | R9: Autres frais
H10: =E10+F10+G10 | J10: =H10*(1+I10) | L10: =SUMIFS('HISTORIQUE DOCS'!$H$4:$H$1000,'HISTORIQUE DOCS'!$F$4:$F$1000,A10,'HISTORIQUE DOCS'!$C$4:$C$1000,"FACTURE",'HISTORIQUE DOCS'!$P$4:$P$1000,"VALIDÉ") | M10: =K10-L10 | R10: Marge % | S10: 0.3
H11: =E11+F11+G11 | J11: =H11*(1+I11) | L11: =SUMIFS('HISTORIQUE DOCS'!$H$4:$H$1000,'HISTORIQUE DOCS'!$F$4:$F$1000,A11,'HISTORIQUE DOCS'!$C$4:$C$1000,"FACTURE",'HISTORIQUE DOCS'!$P$4:$P$1000,"VALIDÉ") | M11: =K11-L11 | R11: Quantité entrée
H12: =E12+F12+G12 | J12: =H12*(1+I12) | L12: =SUMIFS('HISTORIQUE DOCS'!$H$4:$H$1000,'HISTORIQUE DOCS'!$F$4:$F$1000,A12,'HISTORIQUE DOCS'!$C$4:$C$1000,"FACTURE",'HISTORIQUE DOCS'!$P$4:$P$1000,"VALIDÉ") | M12: =K12-L12 | R12: Seuil alerte | S12: 2
H13: =E13+F13+G13 | J13: =H13*(1+I13) | L13: =SUMIFS('HISTORIQUE DOCS'!$H$4:$H$1000,'HISTORIQUE DOCS'!$F$4:$F$1000,A13,'HISTORIQUE DOCS'!$C$4:$C$1000,"FACTURE",'HISTORIQUE DOCS'!$P$4:$P$1000,"VALIDÉ") | M13: =K13-L13 | R13: Garantie
H14: =E14+F14+G14 | J14: =H14*(1+I14) | L14: =SUMIFS('HISTORIQUE DOCS'!$H$4:$H$1000,'HISTORIQUE DOCS'!$F$4:$F$1000,A14,'HISTORIQUE DOCS'!$C$4:$C$1000,"FACTURE",'HISTORIQUE DOCS'!$P$4:$P$1000,"VALIDÉ") | M14: =K14-L14
H15: =E15+F15+G15 | J15: =H15*(1+I15) | L15: =SUMIFS('HISTORIQUE DOCS'!$H$4:$H$1000,'HISTORIQUE DOCS'!$F$4:$F$1000,A15,'HISTORIQUE DOCS'!$C$4:$C$1000,"FACTURE",'HISTORIQUE DOCS'!$P$4:$P$1000,"VALIDÉ") | M15: =K15-L15 | R15: ➕ ENREGISTRER ARTICLE (Bouton maquette)
H16: =E16+F16+G16 | J16: =H16*(1+I16) | L16: =SUMIFS('HISTORIQUE DOCS'!$H$4:$H$1000,'HISTORIQUE DOCS'!$F$4:$F$1000,A16,'HISTORIQUE DOCS'!$C$4:$C$1000,"FACTURE",'HISTORIQUE DOCS'!$P$4:$P$1000,"VALIDÉ") | M16: =K16-L16
H17: =E17+F17+G17 | J17: =H17*(1+I17) | L17: =SUMIFS('HISTORIQUE DOCS'!$H$4:$H$1000,'HISTORIQUE DOCS'!$F$4:$F$1000,A17,'HISTORIQUE DOCS'!$C$4:$C$1000,"FACTURE",'HISTORIQUE DOCS'!$P$4:$P$1000,"VALIDÉ") | M17: =K17-L17
H18: =E18+F18+G18 | J18: =H18*(1+I18) | L18: =SUMIFS('HISTORIQUE DOCS'!$H$4:$H$1000,'HISTORIQUE DOCS'!$F$4:$F$1000,A18,'HISTORIQUE DOCS'!$C$4:$C$1000,"FACTURE",'HISTORIQUE DOCS'!$P$4:$P$1000,"VALIDÉ") | M18: =K18-L18
H19: =E19+F19+G19 | J19: =H19*(1+I19) | L19: =SUMIFS('HISTORIQUE DOCS'!$H$4:$H$1000,'HISTORIQUE DOCS'!$F$4:$F$1000,A19,'HISTORIQUE DOCS'!$C$4:$C$1000,"FACTURE",'HISTORIQUE DOCS'!$P$4:$P$1000,"VALIDÉ") | M19: =K19-L19
H20: =E20+F20+G20 | J20: =H20*(1+I20) | L20: =SUMIFS('HISTORIQUE DOCS'!$H$4:$H$1000,'HISTORIQUE DOCS'!$F$4:$F$1000,A20,'HISTORIQUE DOCS'!$C$4:$C$1000,"FACTURE",'HISTORIQUE DOCS'!$P$4:$P$1000,"VALIDÉ") | M20: =K20-L20
H21: =E21+F21+G21 | J21: =H21*(1+I21) | L21: =SUMIFS('HISTORIQUE DOCS'!$H$4:$H$1000,'HISTORIQUE DOCS'!$F$4:$F$1000,A21,'HISTORIQUE DOCS'!$C$4:$C$1000,"FACTURE",'HISTORIQUE DOCS'!$P$4:$P$1000,"VALIDÉ") | M21: =K21-L21
H22: =E22+F22+G22 | J22: =H22*(1+I22) | L22: =SUMIFS('HISTORIQUE DOCS'!$H$4:$H$1000,'HISTORIQUE DOCS'!$F$4:$F$1000,A22,'HISTORIQUE DOCS'!$C$4:$C$1000,"FACTURE",'HISTORIQUE DOCS'!$P$4:$P$1000,"VALIDÉ") | M22: =K22-L22
H23: =E23+F23+G23 | J23: =H23*(1+I23) | L23: =SUMIFS('HISTORIQUE DOCS'!$H$4:$H$1000,'HISTORIQUE DOCS'!$F$4:$F$1000,A23,'HISTORIQUE DOCS'!$C$4:$C$1000,"FACTURE",'HISTORIQUE DOCS'!$P$4:$P$1000,"VALIDÉ") | M23: =K23-L23
H24: =E24+F24+G24 | J24: =H24*(1+I24) | L24: =SUMIFS('HISTORIQUE DOCS'!$H$4:$H$1000,'HISTORIQUE DOCS'!$F$4:$F$1000,A24,'HISTORIQUE DOCS'!$C$4:$C$1000,"FACTURE",'HISTORIQUE DOCS'!$P$4:$P$1000,"VALIDÉ") | M24: =K24-L24
H25: =E25+F25+G25 | J25: =H25*(1+I25) | L25: =SUMIFS('HISTORIQUE DOCS'!$H$4:$H$1000,'HISTORIQUE DOCS'!$F$4:$F$1000,A25,'HISTORIQUE DOCS'!$C$4:$C$1000,"FACTURE",'HISTORIQUE DOCS'!$P$4:$P$1000,"VALIDÉ") | M25: =K25-L25
H26: =E26+F26+G26 | J26: =H26*(1+I26) | L26: =SUMIFS('HISTORIQUE DOCS'!$H$4:$H$1000,'HISTORIQUE DOCS'!$F$4:$F$1000,A26,'HISTORIQUE DOCS'!$C$4:$C$1000,"FACTURE",'HISTORIQUE DOCS'!$P$4:$P$1000,"VALIDÉ") | M26: =K26-L26
H27: =E27+F27+G27 | J27: =H27*(1+I27) | L27: =SUMIFS('HISTORIQUE DOCS'!$H$4:$H$1000,'HISTORIQUE DOCS'!$F$4:$F$1000,A27,'HISTORIQUE DOCS'!$C$4:$C$1000,"FACTURE",'HISTORIQUE DOCS'!$P$4:$P$1000,"VALIDÉ") | M27: =K27-L27
... H500: =E500+F500+G500 | J500: =H500*(1+I500) | L500: =SUMIFS('HISTORIQUE DOCS'!$H$4:$H$1000,'HISTORIQUE DOCS'!$F$4:$F$1000,A500,'HISTORIQUE DOCS'!$C$4:$C$1000,"FACTURE",'HISTORIQUE DOCS'!$P$4:$P$1000,"VALIDÉ") | M500: =K500-L500

Sheet ENTREES STOCK
A1: FORMULAIRE & JOURNAL DES ENTRÉES DE STOCK
A3: FORMULAIRE | B3: SAISIE | D3: Date | E3: N° Mouvement | F3: Référence | G3: Désignation | H3: Fournisseur | I3: Qté entrée | J3: Coût unitaire | K3: Transport | L3: Autres frais
A4: Date | B4: 46266 | D4: 46235 | E4: ENT-0001 | F4: ART-0001 | G4: Radio Android Mercedes-Benz | H4: Fournisseur A | I4: 5 | J4: 100 | K4: 20 | L4: 0
A5: Référence article | B5: ART-0001 | D5: 46236 | E5: ENT-0002 | F5: ART-0002 | G5: Jante auto + capuchon central | H5: Fournisseur B | I5: 8 | J5: 250 | K5: 200 | L5: 0
A6: Fournisseur | B6: Fournisseur A | D6: 46237 | E6: ENT-0003 | F6: ART-0003 | G6: Samsung Galaxy A17 128G + 6G | H6: Fournisseur C | I6: 6 | J6: 220 | K6: 90 | L6: 0
A7: Quantité reçue | B7: 5 | D7: 46238 | E7: ENT-0004 | F7: SRV-0001 | G7: Diagnostic automobile | H7: Interne | I7: 999 | J7: 0 | K7: 0 | L7: 0
A8: Coût achat unitaire | B8: 100
A9: Transport global | B9: 20
A10: Autres frais | B10: 0
A11: Réf. facture fournisseur | B11: FOUR-2026-001
A13: ✅ VALIDER L’ENTRÉE STOCK (Bouton maquette)

Sheet HISTORIQUE DOCS
A1: HISTORIQUE DES FACTURES & PROFORMAS
A3: Date | B3: N° Document | C3: Type | D3: ID Client | E3: Client | F3: Référence Article | G3: Désignation | H3: Qté | I3: Prix unitaire | J3: Transport | K3: Autres frais | L3: Marge % | M3: Sous-total | N3: Marge $ | O3: Total | P3: Statut
A4: 46244 | B4: KTC-FAC-2026-001 | C4: FACTURE | D4: CLI-0001 | E4: NONO DIENGA | F4: PACK-AUDIO | G4: Pack audio complet | H4: 1 | I4: 1820 | J4: 459 | K4: 0 | L4: 0.3 | M4: =H4*I4+J4+K4 | N4: =M4*L4 | O4: =M4+N4 | P4: VALIDÉ
A5: 46244 | B5: KTC-PF-2026-002 | C5: PROFORMA | D5: CLI-0002 | E5: SONY MUKAZA SCHADRAK | F5: ART-0002 | G5: Jante auto + capuchon central | H5: 4 | I5: 250 | J5: 200 | K5: 0 | L5: 0.3 | M5: =H5*I5+J5+K5 | N5: =M5*L5 | O5: =M5+N5 | P5: VALIDÉ
A6: 46248 | B6: KTC-FAC-2026-002 | C6: FACTURE | D6: CLI-0003 | E6: MATHIEU KAYISA | F6: ART-0001 | G6: Radio Android Mercedes-Benz | H6: 1 | I6: 100 | J6: 20 | K6: 0 | L6: 0.3 | M6: =H6*I6+J6+K6 | N6: =M6*L6 | O6: =M6+N6 | P6: VALIDÉ
A7: 46266 | B7: KTC-PF-2026-003 | C7: PROFORMA | D7: CLI-0004 | E7: CLIENT DEMO | F7: ART-0003 | G7: Samsung Galaxy A17 128G + 6G | H7: 1 | I7: 300 | J7: 15 | K7: 0 | L7: 0.3 | M7: =H7*I7+J7+K7 | N7: =M7*L7 | O7: =M7+N7 | P7: BROUILLON
M8: =H8*I8+J8+K8 | N8: =M8*L8 | O8: =M8+N8
M9: =H9*I9+J9+K9 | N9: =M9*L9 | O9: =M9+N9
M10: =H10*I10+J10+K10 | N10: =M10*L10 | O10: =M10+N10
M11: =H11*I11+J11+K11 | N11: =M11*L11 | O11: =M11+N11
M12: =H12*I12+J12+K12 | N12: =M12*L12 | O12: =M12+N12
M13: =H13*I13+J13+K13 | N13: =M13*L13 | O13: =M13+N13
M14: =H14*I14+J14+K14 | N14: =M14*L14 | O14: =M14+N14
M15: =H15*I15+J15+K15 | N15: =M15*L15 | O15: =M15+N15
M16: =H16*I16+J16+K16 | N16: =M16*L16 | O16: =M16+N16
M17: =H17*I17+J17+K17 | N17: =M17*L17 | O17: =M17+N17
M18: =H18*I18+J18+K18 | N18: =M18*L18 | O18: =M18+N18
M19: =H19*I19+J19+K19 | N19: =M19*L19 | O19: =M19+N19
... M1000: =H1000*I1000+J1000+K1000 | N1000: =M1000*L1000 | O1000: =M1000+N1000

Sheet JOURNAL STOCK
A1: JOURNAL DE STOCK — ENTRÉES / SORTIES
A3: Date | B3: Type mouvement | C3: Référence | D3: Désignation | E3: Document | F3: Qté entrée | G3: Qté sortie | H3: Stock après | I3: Client / Fournisseur | J3: Observation
A4: 46235 | B4: ENTRÉE | C4: ART-0001 | D4: Radio Android Mercedes-Benz | E4: ENT-0001 | F4: 5 | G4: 0 | H4: 5 | I4: Fournisseur A
A5: 46236 | B5: ENTRÉE | C5: ART-0002 | D5: Jante auto + capuchon central | E5: ENT-0002 | F5: 8 | G5: 0 | H5: 8 | I5: Fournisseur B
A6: 46237 | B6: ENTRÉE | C6: ART-0003 | D6: Samsung Galaxy A17 128G + 6G | E6: ENT-0003 | F6: 6 | G6: 0 | H6: 6 | I6: Fournisseur C
A7: 46248 | B7: SORTIE | C7: ART-0001 | D7: Radio Android Mercedes-Benz | E7: KTC-FAC-2026-002 | F7: 0 | G7: 1 | H7: 4 | I7: MATHIEU KAYISA | J7: Sortie automatique par facture validée
A8: 46249 | B8: SORTIE | C8: ART-0002 | D8: Jante auto + capuchon central | E8: KTC-FAC-2026-003 | F8: 0 | G8: 2 | H8: 6 | I8: Client Démo | J8: Exemple
A9: 46266 | B9: ENTRÉE | C9: ART-0001 | D9: Radio Android Mercedes-Benz | E9: ENT-0005 | F9: 2 | G9: 0 | H9: 6 | I9: Fournisseur A | J9: Réapprovisionnement

Sheet TABLEAU DE BORD
A1: KATANGA TECHCARE — TABLEAU DE BORD
A3: Indicateur | B3: Valeur | D3: Indicateur | E3: Valeur | G3: Indicateur | H3: Valeur
A4: Factures validées | B4: =COUNTIFS('HISTORIQUE DOCS'!C4:C1000,"FACTURE",'HISTORIQUE DOCS'!P4:P1000,"VALIDÉ") | D4: Clients | E4: =COUNTA('BASE CLIENTS'!A4:A500) | G4: Créances | H4: 0
A5: Proformas | B5: =COUNTIF('HISTORIQUE DOCS'!C4:C1000,"PROFORMA") | D5: Articles actifs | E5: =COUNTA('BASE ARTICLES'!A4:A500) | G5: Dépenses | H5: 0
A6: CA facturé | B6: =SUMIFS('HISTORIQUE DOCS'!O4:O1000,'HISTORIQUE DOCS'!C4:C1000,"FACTURE",'HISTORIQUE DOCS'!P4:P1000,"VALIDÉ") | D6: Stock total | E6: =SUM('BASE ARTICLES'!M4:M500) | G6: Charges | H6: 0
A7: Marge commerciale | B7: =SUMIFS('HISTORIQUE DOCS'!N4:N1000,'HISTORIQUE DOCS'!C4:C1000,"FACTURE",'HISTORIQUE DOCS'!P4:P1000,"VALIDÉ") | D7: Valeur stock coût | E7: =SUMPRODUCT('BASE ARTICLES'!M4:M500,'BASE ARTICLES'!H4:H500) | G7: Résultat net | H7: 0
A8: Articles en alerte | B8: =SUMPRODUCT(--('BASE ARTICLES'!A4:A500<>""),--('BASE ARTICLES'!M4:M500<='BASE ARTICLES'!N4:N500)) | D8: Ventes du mois | E8: =COUNTIFS('HISTORIQUE DOCS'!A4:A1000,">="&DATE(YEAR(TODAY()),MONTH(TODAY()),1),'HISTORIQUE DOCS'!A4:A1000,"<"&DATE(YEAR(TODAY()),MONTH(TODAY())+1,1),'HISTORIQUE DOCS'!C4:C1000,"FACTURE") | G8: Documents brouillon | H8: =COUNTIF('HISTORIQUE DOCS'!P4:P1000,"BROUILLON")

Sheet PARAMETRES
A1: KATANGA TECHCARE — PARAMÈTRES
A3: Paramètre | B3: Valeur
A4: Entreprise | B4: KATANGA TECHCARE
A5: WhatsApp | B5: +243 826 787 602
A6: Adresse | B6: Avenue Mama Yemo n°2254, Commune de Lubumbashi
A7: Référence | B7: ANAPI Lubumbashi, Haut-Katanga, RDC
A8: Devise | B8: USD
A9: Marge société par défaut | B9: 0.3
A10: Année | B10: 2026
A11: Préfixe Facture | B11: KTC-FAC
A12: Préfixe Proforma | B12: KTC-PF
A13: Statut stock facture | B13: VALIDÉ
A14: Statut proforma | B14: VALIDÉ
A15: Conditions de paiement | B15: 50% à la commande / 50% au retrait
A16: Validité proforma (jours) | B16: 15
A17: Format d’impression du document | B17: A5 portrait (1 page)
A18: Nombre de lignes article par document | B18: 10
